pyro_cg/__init__.py
pyro_cg/causal_graph.py
pyro_cg/cg_node.py
pyro_cg/gen_test_data.py
pyro_cg/graph_node.py
pyro_cg-0.0.3.dist-info/LICENSE
pyro_cg-0.0.3.dist-info/METADATA
pyro_cg-0.0.3.dist-info/WHEEL
pyro_cg-0.0.3.dist-info/top_level.txt
pyro_cg-0.0.3.dist-info/RECORD
